Metadata-Version: 2.1
Name: DiscordUtilsMod
Version: 1.1
Summary: DiscordUtils is a very useful library made to be used with discord.py
Home-page: https://www.github.com/amirdadfar9192/DiscordUtils
Author: toxicrecker MODDIFIED BY AMIRDADFAR9192
License: UNKNOWN
Platform: UNKNOWN
Classifier: Programming Language :: Python :: 3
Classifier: License :: OSI Approved :: MIT License
Classifier: Operating System :: OS Independent
Requires-Python: >= 3.6
Provides-Extra: voice
License-File: LICENSE.txt
